unique_package/__init__.py
unique_package/unique_function.py
unique_function-0.0.7.dist-info/LICENSE
unique_function-0.0.7.dist-info/METADATA
unique_function-0.0.7.dist-info/WHEEL
unique_function-0.0.7.dist-info/top_level.txt
unique_function-0.0.7.dist-info/RECORD
