Metadata-Version: 2.1
Name: unique-function
Version: 0.0.7
Summary: function to define unique characters
Home-page: https://git.foxminded.com.ua/foxstudent101526/packaging
Author: Bartkiv-Yuriy
Author-email: author@example.com
Classifier: Programming Language :: Python :: 3
Classifier: License :: OSI Approved :: MIT License
Classifier: Operating System :: OS Independent
Requires-Python: >=3.8
License-File: LICENSE
